Compiled from asdf.f
public class Arithmetic extends java.lang.Object {
    public Arithmetic();
    public static void main(java.lang.String[]);
    public static void test_add();
    public static void test_sub();
    public static void test_mul();
    public static void test_div();
    public static void test_rem();
    public static void test_neg();
    public static void test_shift();
    public static void test_bitwise_or();
    public static void test_bitwise_and();
    public static void test_bitwise_xor();
    public static void test_comparison();
}

Method Arithmetic()
   0 aload_0
   1 invokespecial #11 <Method java.lang.Object()>
   4 return

Method void main(java.lang.String[])
   0 invokestatic #16 <Method void test_add()>
   3 invokestatic #19 <Method void test_sub()>
   6 invokestatic #22 <Method void test_mul()>
   9 invokestatic #25 <Method void test_div()>
  12 invokestatic #28 <Method void test_rem()>
  15 invokestatic #31 <Method void test_neg()>
  18 invokestatic #34 <Method void test_shift()>
  21 invokestatic #37 <Method void test_bitwise_or()>
  24 invokestatic #40 <Method void test_bitwise_and()>
  27 invokestatic #43 <Method void test_bitwise_xor()>
  30 invokestatic #46 <Method void test_comparison()>
  33 return

Method void test_add()
   0 iconst_1
   1 istore_0
   2 iconst_2
   3 istore_1
   4 lconst_1
   5 lstore_2
   6 ldc2_w #47 <Long 2>
   9 lstore 4
  11 fconst_1
  12 fstore 6
  14 fconst_2
  15 fstore 7
  17 dconst_1
  18 dstore 8
  20 ldc2_w #49 <Double 2.0>
  23 dstore 10
  25 iload_0
  26 iload_0
  27 iadd
  28 iload_1
  29 if_icmpne 72
  32 lload_2
  33 lload_2
  34 ladd
  35 lload 4
  37 lcmp
  38 ifne 72
  41 fload 6
  43 fload 6
  45 fadd
  46 fload 7
  48 fcmpl
  49 ifne 72
  52 dload 8
  54 dload 8
  56 dadd
  57 dload 10
  59 dcmpl
  60 ifne 72
  63 getstatic #56 <Field java.io.PrintStream out>
  66 ldc #58 <String "Addition:          OK">
  68 invokevirtual #64 <Method void println(java.lang.String)>
  71 return
  72 getstatic #56 <Field java.io.PrintStream out>
  75 ldc #66 <String "Addition:          Failed">
  77 invokevirtual #64 <Method void println(java.lang.String)>
  80 return

Method void test_sub()
   0 iconst_1
   1 istore_0
   2 iconst_0
   3 istore_1
   4 lconst_1
   5 lstore_2
   6 lconst_0
   7 lstore 4
   9 fconst_1
  10 fstore 6
  12 fconst_0
  13 fstore 7
  15 dconst_1
  16 dstore 8
  18 dconst_0
  19 dstore 10
  21 iload_0
  22 iload_0
  23 isub
  24 iload_1
  25 if_icmpne 68
  28 lload_2
  29 lload_2
  30 lsub
  31 lload 4
  33 lcmp
  34 ifne 68
  37 fload 6
  39 fload 6
  41 fsub
  42 fload 7
  44 fcmpl
  45 ifne 68
  48 dload 8
  50 dload 8
  52 dsub
  53 dload 10
  55 dcmpl
  56 ifne 68
  59 getstatic #56 <Field java.io.PrintStream out>
  62 ldc #68 <String "Subtraction:       OK">
  64 invokevirtual #64 <Method void println(java.lang.String)>
  67 return
  68 getstatic #56 <Field java.io.PrintStream out>
  71 ldc #70 <String "Subtraction:       Failed">
  73 invokevirtual #64 <Method void println(java.lang.String)>
  76 return

Method void test_mul()
   0 iconst_1
   1 istore_0
   2 iconst_2
   3 istore_1
   4 lconst_1
   5 lstore_2
   6 ldc2_w #47 <Long 2>
   9 lstore 4
  11 fconst_1
  12 fstore 6
  14 fconst_2
  15 fstore 7
  17 dconst_1
  18 dstore 8
  20 ldc2_w #49 <Double 2.0>
  23 dstore 10
  25 iload_0
  26 iload_1
  27 imul
  28 iload_1
  29 if_icmpne 73
  32 lload_2
  33 lload 4
  35 lmul
  36 lload 4
  38 lcmp
  39 ifne 73
  42 fload 6
  44 fload 7
  46 fmul
  47 fload 7
  49 fcmpl
  50 ifne 73
  53 dload 8
  55 dload 10
  57 dmul
  58 dload 10
  60 dcmpl
  61 ifne 73
  64 getstatic #56 <Field java.io.PrintStream out>
  67 ldc #72 <String "Multiplication:    OK">
  69 invokevirtual #64 <Method void println(java.lang.String)>
  72 return
  73 getstatic #56 <Field java.io.PrintStream out>
  76 ldc #74 <String "Multiplication:    Failed">
  78 invokevirtual #64 <Method void println(java.lang.String)>
  81 return

Method void test_div()
   0 iconst_4
   1 istore_0
   2 iconst_2
   3 istore_1
   4 ldc2_w #75 <Long 4>
   7 lstore_2
   8 ldc2_w #47 <Long 2>
  11 lstore 4
  13 ldc #77 <Real 4.0>
  15 fstore 6
  17 fconst_2
  18 fstore 7
  20 ldc2_w #78 <Double 4.0>
  23 dstore 8
  25 ldc2_w #49 <Double 2.0>
  28 dstore 10
  30 iload_0
  31 iload_1
  32 idiv
  33 iload_1
  34 if_icmpne 78
  37 lload_2
  38 lload 4
  40 ldiv
  41 lload 4
  43 lcmp
  44 ifne 78
  47 fload 6
  49 fload 7
  51 fdiv
  52 fload 7
  54 fcmpl
  55 ifne 78
  58 dload 8
  60 dload 10
  62 ddiv
  63 dload 10
  65 dcmpl
  66 ifne 78
  69 getstatic #56 <Field java.io.PrintStream out>
  72 ldc #81 <String "Division:          OK">
  74 invokevirtual #64 <Method void println(java.lang.String)>
  77 return
  78 getstatic #56 <Field java.io.PrintStream out>
  81 ldc #83 <String "Division:          Failed">
  83 invokevirtual #64 <Method void println(java.lang.String)>
  86 return

Method void test_rem()
   0 iconst_1
   1 istore_0
   2 iconst_2
   3 istore_1
   4 bipush 11
   6 istore_2
   7 lconst_1
   8 lstore_3
   9 ldc2_w #47 <Long 2>
  12 lstore 5
  14 ldc2_w #84 <Long 11>
  17 lstore 7
  19 fconst_1
  20 fstore 9
  22 fconst_2
  23 fstore 10
  25 ldc #86 <Real 11.0>
  27 fstore 11
  29 dconst_1
  30 dstore 12
  32 ldc2_w #49 <Double 2.0>
  35 dstore 14
  37 ldc2_w #87 <Double 11.0>
  40 dstore 16
  42 iload_2
  43 iload_1
  44 irem
  45 iload_0
  46 if_icmpne 90
  49 lload 7
  51 lload 5
  53 lrem
  54 lload_3
  55 lcmp
  56 ifne 90
  59 fload 11
  61 fload 10
  63 frem
  64 fload 9
  66 fcmpl
  67 ifne 90
  70 dload 16
  72 dload 14
  74 drem
  75 dload 12
  77 dcmpl
  78 ifne 90
  81 getstatic #56 <Field java.io.PrintStream out>
  84 ldc #90 <String "Remainder:         OK">
  86 invokevirtual #64 <Method void println(java.lang.String)>
  89 return
  90 getstatic #56 <Field java.io.PrintStream out>
  93 ldc #92 <String "Remainder:         Failed">
  95 invokevirtual #64 <Method void println(java.lang.String)>
  98 return

Method void test_neg()
   0 bipush -2
   2 istore_0
   3 iconst_2
   4 istore_1
   5 ldc2_w #93 <Long -2>
   8 lstore_2
   9 ldc2_w #47 <Long 2>
  12 lstore 4
  14 ldc #95 <Real -2.0>
  16 fstore 6
  18 fconst_2
  19 fstore 7
  21 ldc2_w #96 <Double -2.0>
  24 dstore 8
  26 ldc2_w #49 <Double 2.0>
  29 dstore 10
  31 iload_1
  32 ineg
  33 iload_0
  34 if_icmpne 72
  37 lload 4
  39 lneg
  40 lload_2
  41 lcmp
  42 ifne 72
  45 fload 7
  47 fneg
  48 fload 6
  50 fcmpl
  51 ifne 72
  54 dload 10
  56 dneg
  57 dload 8
  59 dcmpl
  60 ifne 72
  63 getstatic #56 <Field java.io.PrintStream out>
  66 ldc #99 <String "Negation:          OK">
  68 invokevirtual #64 <Method void println(java.lang.String)>
  71 return
  72 getstatic #56 <Field java.io.PrintStream out>
  75 ldc #101 <String "Negation:          Failed">
  77 invokevirtual #64 <Method void println(java.lang.String)>
  80 return

Method void test_shift()
   0 iconst_1
   1 istore_0
   2 iconst_2
   3 istore_1
   4 lconst_1
   5 lstore_2
   6 ldc2_w #47 <Long 2>
   9 lstore 4
  11 iload_0
  12 iload_0
  13 ishl
  14 iload_1
  15 if_icmpne 68
  18 lload_2
  19 iload_0
  20 lshl
  21 lload 4
  23 lcmp
  24 ifne 68
  27 iload_1
  28 iload_0
  29 ishr
  30 iload_0
  31 if_icmpne 68
  34 lload 4
  36 iload_0
  37 lshr
  38 lload_2
  39 lcmp
  40 ifne 68
  43 iload_1
  44 iload_0
  45 iushr
  46 iload_0
  47 if_icmpne 68
  50 lload 4
  52 iload_0
  53 lushr
  54 lload_2
  55 lcmp
  56 ifne 68
  59 getstatic #56 <Field java.io.PrintStream out>
  62 ldc #103 <String "Shift:             OK">
  64 invokevirtual #64 <Method void println(java.lang.String)>
  67 return
  68 getstatic #56 <Field java.io.PrintStream out>
  71 ldc #105 <String "Shift:             Failed">
  73 invokevirtual #64 <Method void println(java.lang.String)>
  76 return

Method void test_bitwise_or()
   0 iconst_1
   1 istore_0
   2 iconst_2
   3 istore_1
   4 iconst_3
   5 istore_2
   6 lconst_1
   7 lstore_3
   8 ldc2_w #47 <Long 2>
  11 lstore 5
  13 ldc2_w #106 <Long 3>
  16 lstore 7
  18 iload_0
  19 iload_1
  20 ior
  21 iload_2
  22 if_icmpne 44
  25 lload_3
  26 lload 5
  28 lor
  29 lload 7
  31 lcmp
  32 ifne 44
  35 getstatic #56 <Field java.io.PrintStream out>
  38 ldc #109 <String "Bitwise OR:        OK">
  40 invokevirtual #64 <Method void println(java.lang.String)>
  43 return
  44 getstatic #56 <Field java.io.PrintStream out>
  47 ldc #111 <String "Bitwise OR:        Failed">
  49 invokevirtual #64 <Method void println(java.lang.String)>
  52 return

Method void test_bitwise_and()
   0 iconst_1
   1 istore_0
   2 iconst_2
   3 istore_1
   4 iconst_0
   5 istore_2
   6 lconst_1
   7 lstore_3
   8 ldc2_w #47 <Long 2>
  11 lstore 5
  13 lconst_0
  14 lstore 7
  16 iload_0
  17 iload_1
  18 iand
  19 iload_2
  20 if_icmpne 42
  23 lload_3
  24 lload 5
  26 land
  27 lload 7
  29 lcmp
  30 ifne 42
  33 getstatic #56 <Field java.io.PrintStream out>
  36 ldc #113 <String "Bitwise AND:       OK">
  38 invokevirtual #64 <Method void println(java.lang.String)>
  41 return
  42 getstatic #56 <Field java.io.PrintStream out>
  45 ldc #115 <String "Bitwise AND:       Failed">
  47 invokevirtual #64 <Method void println(java.lang.String)>
  50 return

Method void test_bitwise_xor()
   0 iconst_1
   1 istore_0
   2 iconst_2
   3 istore_1
   4 iconst_3
   5 istore_2
   6 lconst_1
   7 lstore_3
   8 ldc2_w #47 <Long 2>
  11 lstore 5
  13 ldc2_w #106 <Long 3>
  16 lstore 7
  18 iload_0
  19 iload_1
  20 ixor
  21 iload_2
  22 if_icmpne 44
  25 lload_3
  26 lload 5
  28 lxor
  29 lload 7
  31 lcmp
  32 ifne 44
  35 getstatic #56 <Field java.io.PrintStream out>
  38 ldc #117 <String "Bitwise XOR:       OK">
  40 invokevirtual #64 <Method void println(java.lang.String)>
  43 return
  44 getstatic #56 <Field java.io.PrintStream out>
  47 ldc #119 <String "Bitwise XOR:       Failed">
  49 invokevirtual #64 <Method void println(java.lang.String)>
  52 return

Method void test_comparison()
   0 ldc2_w #47 <Long 2>
   3 lstore_0
   4 ldc2_w #84 <Long 11>
   7 lstore_2
   8 fconst_2
   9 fstore 4
  11 ldc #86 <Real 11.0>
  13 fstore 5
  15 ldc2_w #49 <Double 2.0>
  18 dstore 6
  20 ldc2_w #87 <Double 11.0>
  23 dstore 8
  25 lload_2
  26 lload_0
  27 lcmp
  28 ifle 72
  31 fload 5
  33 fload 4
  35 fcmpl
  36 ifle 72
  39 fload 4
  41 fload 5
  43 fcmpg
  44 ifge 72
  47 dload 8
  49 dload 6
  51 dcmpl
  52 ifle 72
  55 dload 6
  57 dload 8
  59 dcmpg
  60 ifge 72
  63 getstatic #56 <Field java.io.PrintStream out>
  66 ldc #121 <String "Comparison:        OK">
  68 invokevirtual #64 <Method void println(java.lang.String)>
  71 return
  72 getstatic #56 <Field java.io.PrintStream out>
  75 ldc #123 <String "Comparison:        Failed">
  77 invokevirtual #64 <Method void println(java.lang.String)>
  80 return
