Compiled from "iinc.f"
public class Iinc extends java.lang.Object{
public Iinc();
  Code:
   0:	aload_0
   1:	invokespecial	#11; //Method java/lang/Object."<init>":()V
   4:	return




public static void main(java.lang.String[]);
  Code:
   0:	iconst_0
   1:	istore_1
   2:	iconst_0
   3:	istore	255
   5:	iconst_0
   6:	istore_w 300
   10:	iinc	1, -1
   13:	iinc	255, -1
   16:	iinc_w 300, -1
   22:	iinc	255, 127
   25:	iinc_w 255, 300
   31:	iinc	255, -127
   34:	iinc	255, -128
   37:	iinc_w 255, -129
   43:	return




}

