Compiled from "asdf.f"
public class Synchronization extends java.lang.Object{
public Synchronization();
  Code:
   0:	aload_0
   1:	invokespecial	#11; //Method java/lang/Object."<init>":()V
   4:	return




public void foo();
  Code:
   0:	aload_0
   1:	monitorenter
   2:	getstatic	#18; //Field java/lang/System.out:Ljava/io/PrintStream;
   5:	ldc	#20; //String hello...
   7:	invokevirtual	#26; //Method java/io/PrintStream.println:(Ljava/lang/String;)V
   10:	aload_0
   11:	monitorexit
   12:	return
   13:	astore_1
   14:	aload_0
   15:	monitorexit
   16:	aload_1
   17:	athrow
   18:	return
  Exception table:
   from   to  target type
     2    12    13   any
    13    16    13   any




public static void main(java.lang.String[]);
  Code:
   0:	new	#2; //class Synchronization
   3:	dup
   4:	invokespecial	#29; //Method "<init>":()V
   7:	invokevirtual	#31; //Method foo:()V
   10:	return




}

