Compiled from asdf.f
public class Goto extends java.lang.Object {
    public Goto();
    public static void main(java.lang.String[]);
}

Method Goto()
   0 aload_0
   1 invokespecial #11 <Method java.lang.Object()>
   4 return

Method void main(java.lang.String[])
   0 goto 11
   3 getstatic #19 <Field java.io.PrintStream out>
   6 ldc #27 <String "bad">
   8 invokevirtual #25 <Method void println(java.lang.String)>
  11 getstatic #19 <Field java.io.PrintStream out>
  14 ldc #29 <String "good">
  16 invokevirtual #25 <Method void println(java.lang.String)>
  19 goto 30
  22 getstatic #19 <Field java.io.PrintStream out>
  25 ldc #27 <String "bad">
  27 invokevirtual #25 <Method void println(java.lang.String)>
  30 getstatic #19 <Field java.io.PrintStream out>
  33 ldc #29 <String "good">
  35 invokevirtual #25 <Method void println(java.lang.String)>
  38 return
