Compiled from "asdf.f"
public class ObjectCreation extends java.lang.Object{
public int x;

public static int y;

public ObjectCreation();
  Code:
   0:	aload_0
   1:	invokespecial	#11; //Method java/lang/Object."<init>":()V
   4:	return




public void foo();
  Code:
   0:	return




public static void main(java.lang.String[]);
  Code:
   0:	new	#2; //class ObjectCreation
   3:	dup
   4:	invokespecial	#18; //Method "<init>":()V
   7:	astore_1
   8:	aload_1
   9:	invokevirtual	#20; //Method foo:()V
   12:	bipush	6
   14:	iconst_2
   15:	multianewarray	#22,  2; //class "[[I"
   19:	astore_2
   20:	aload_2
   21:	iconst_3
   22:	aaload
   23:	iconst_1
   24:	iconst_5
   25:	iastore
   26:	aload_2
   27:	arraylength
   28:	aload_1
   29:	aload_1
   30:	getfield	#24; //Field x:I
   33:	sipush	666
   36:	iadd
   37:	putfield	#24; //Field x:I
   40:	getstatic	#26; //Field y:I
   43:	sipush	666
   46:	iadd
   47:	putstatic	#26; //Field y:I
   50:	aload_1
   51:	instanceof	#27; //class java/lang/Object
   54:	aload_1
   55:	checkcast	#28; //class java/lang/Object
   58:	return




}

