Compiled from "asdf.f"
public class LineNumbers extends java.lang.Object{
public LineNumbers();
  Code:
   0:	aload_0
   1:	invokespecial	#11; //Method java/lang/Object."<init>":()V
   4:	return


public static void main(java.lang.String[]);
  Code:
   0:	bipush	12
   2:	istore_1
   3:	bipush	34
   5:	istore_2
   6:	bipush	56
   8:	istore_3
   9:	iload_1
   10:	iload_2
   11:	imul
   12:	iload_3
   13:	iconst_2
   14:	isub
   15:	iadd
   16:	istore_3
   17:	iload_3
   18:	sipush	666
   21:	iadd
   22:	istore_3
   23:	return

  LineNumberTable: 
   line 13: 0
   line 14: 3
   line 15: 6
   line 16: 9
   line 17: 17
   line 18: 23

}

