Compiled from "asdf.f"
public class TypeConversion extends java.lang.Object{
public TypeConversion();
  Code:
   0:	aload_0
   1:	invokespecial	#11; //Method java/lang/Object."<init>":()V
   4:	return


public static void main(java.lang.String[]);
  Code:
   0:	bipush	10
   2:	i2l
   3:	lstore_2
   4:	bipush	10
   6:	i2f
   7:	fstore	4
   9:	bipush	10
   11:	i2d
   12:	dstore	5
   14:	ldc2_w	#14; //long 10l
   17:	l2f
   18:	fstore	4
   20:	ldc2_w	#14; //long 10l
   23:	l2d
   24:	dstore	5
   26:	ldc	#16; //float 10.0f
   28:	f2d
   29:	dstore	5
   31:	bipush	10
   33:	i2b
   34:	istore	8
   36:	bipush	10
   38:	i2c
   39:	istore	7
   41:	bipush	10
   43:	i2s
   44:	istore	9
   46:	ldc2_w	#14; //long 10l
   49:	l2i
   50:	istore_1
   51:	ldc	#16; //float 10.0f
   53:	f2i
   54:	istore_1
   55:	ldc	#16; //float 10.0f
   57:	f2l
   58:	lstore_2
   59:	ldc2_w	#17; //double 10.0d
   62:	d2i
   63:	istore_1
   64:	ldc2_w	#17; //double 10.0d
   67:	d2l
   68:	lstore_2
   69:	ldc2_w	#17; //double 10.0d
   72:	d2f
   73:	fstore	4
   75:	return


}

