Compiled from iinc.f
public class Iinc extends java.lang.Object {
    public Iinc();
    public static void main(java.lang.String[]);
}

Method Iinc()
   0 aload_0
   1 invokespecial #11 <Method java.lang.Object()>
   4 return

Method void main(java.lang.String[])
   0 iconst_0
   1 istore_1
   2 iconst_0
   3 istore 255
   5 iconst_0
   6 istore_w 300
  10 iinc 1 -1
  13 iinc 255 -1
  16 iinc_w 300 -1
  22 iinc 255 127
  25 iinc_w 255 300
  31 iinc 255 -127
  34 iinc 255 -128
  37 iinc_w 255 -129
  43 return
