Compiled from asdf.f
public class LineNumbers extends java.lang.Object {
    public LineNumbers();
    public static void main(java.lang.String[]);
}

Method LineNumbers()
   0 aload_0
   1 invokespecial #11 <Method java.lang.Object()>
   4 return

Method void main(java.lang.String[])
   0 bipush 12
   2 istore_1
   3 bipush 34
   5 istore_2
   6 bipush 56
   8 istore_3
   9 iload_1
  10 iload_2
  11 imul
  12 iload_3
  13 iconst_2
  14 isub
  15 iadd
  16 istore_3
  17 iload_3
  18 sipush 666
  21 iadd
  22 istore_3
  23 return

Line numbers for method void main(java.lang.String[])
   line 13: 0
   line 14: 3
   line 15: 6
   line 16: 9
   line 17: 17
   line 18: 23
